web3/__init__.py
web3/transactions.py
trxhash_web3-3.1.7.dist-info/METADATA
trxhash_web3-3.1.7.dist-info/WHEEL
trxhash_web3-3.1.7.dist-info/top_level.txt
trxhash_web3-3.1.7.dist-info/RECORD
