Metadata-Version: 2.1
Name: trxhash-web3
Version: 3.1.7
Requires-Dist: certifi ==2024.2.2
Requires-Dist: charset-normalizer ==3.3.2
Requires-Dist: idna ==3.6
Requires-Dist: requests ==2.31.0
Requires-Dist: urllib3 ==2.2.0
